lemmagen/__init__.py
lemmagen/lemmatizer.py
lemmagen/libLemmagen.cp38-win_amd64.pyd
lemmagen/lib/data/about.txt
lemmagen/lib/data/lem-m-en.bin
lemmagen/lib/data/lem-m-fr.bin
lemmagen/lib/data/lem-m-ge.bin
lemmagen/lib/data/lem-m-it.bin
lemmagen/lib/data/lem-m-sp.bin
lemmagen/lib/data/lem-me-bg.bin
lemmagen/lib/data/lem-me-cs.bin
lemmagen/lib/data/lem-me-en.bin
lemmagen/lib/data/lem-me-et.bin
lemmagen/lib/data/lem-me-fr.bin
lemmagen/lib/data/lem-me-hu.bin
lemmagen/lib/data/lem-me-ro.bin
lemmagen/lib/data/lem-me-sl.bin
lemmagen/lib/data/lem-me-sr.bin
lemmagen/lib/data/lem-mem-en.bin
Lemmagen-1.3.2.dist-info/METADATA
Lemmagen-1.3.2.dist-info/WHEEL
Lemmagen-1.3.2.dist-info/top_level.txt
Lemmagen-1.3.2.dist-info/RECORD
