Metadata-Version: 2.1
Name: Lemmagen
Version: 1.3.2
Summary: LemmaGen lemmatizer for Python supporing Slovene, Serbian, Romanian, Estonian, Bulgarian and other languages
Home-page: UNKNOWN
Author: Jernej Virag
Author-email: jernej@virag.si
License: GPLv2+
Platform: UNKNOWN
Classifier: License :: OSI Approved :: GNU General Public License v2 or later (GPLv2+)
Classifier: Operating System :: OS Independent
Classifier: Intended Audience :: Developers
Classifier: Development Status :: 5 - Production/Stable
Classifier: Topic :: Software Development :: Libraries :: Python Modules
Classifier: Programming Language :: Python
Classifier: Programming Language :: Python :: 2
Classifier: Programming Language :: Python :: 3
Classifier: Topic :: Text Processing :: Linguistic
